ramapi/__init__.py
ramapi/ramapi.py
ramapi-0.1.0.dist-info/METADATA
ramapi-0.1.0.dist-info/RECORD
ramapi-0.1.0.dist-info/WHEEL
ramapi-0.1.0.dist-info/entry_points.txt
ramapi-0.1.0.dist-info/top_level.txt
