Metadata-Version: 1.1
Name: ramapi
Version: 0.1.0
Summary: Python implementation for the Rick and Morty API https://rickandmortyapi.com/
Home-page: https://github.com/curiousrohan/ramapi
Author: Rohan Hazra
Author-email: rohanhazra4@gmail.com
License: MIT license
Keywords: ramapi
Platform: UNKNOWN
Classifier: Development Status :: 2 - Pre-Alpha
Classifier: Intended Audience :: Developers
Classifier: License :: OSI Approved :: MIT License
Classifier: Natural Language :: English
Classifier: Programming Language :: Python :: 3
Classifier: Programming Language :: Python :: 3.4
Classifier: Programming Language :: Python :: 3.5
Classifier: Programming Language :: Python :: 3.6
Classifier: Programming Language :: Python :: 3.7
